{
  "preset-001": {
    "id": "preset-001",
    "title": "Grinder",
    "description": "A player who takes no risks, plays with little variety and is willing to play long baseline rallies.",
    "is_default": false,
    "sliders": {
      "fh_power": 40,
      "fh_spin": 80,
      "bh_power": 40,
      "bh_spin": 80,
      "serve_power": 50,
      "serve_spin": 50,
      "shot_dir_risk": 30,
      "serve_variety": 50,
      "drop_frequency": 15,
      "deuce_spin": 50,
      "deuce_place": 50,
      "ad_spin": 50,
      "ad_place": 50,
      "pressure_play_risk": 30,
      "return_position": 90,
      "movement_aggression": 45,
      "time_btwn_points": 75,
      "slice_usage": 60
    },
    "created_at": "2026-02-18T21:09:32.748533+00:00"
  },
  "preset-002": {
    "id": "preset-002",
    "title": "Aggresive All Court Player",
    "description": "",
    "is_default": true,
    "sliders": {
      "fh_power": 70,
      "fh_spin": 40,
      "bh_power": 70,
      "bh_spin": 40,
      "serve_power": 80,
      "serve_spin": 70,
      "shot_dir_risk": 90,
      "serve_variety": 85,
      "drop_frequency": 70,
      "deuce_spin": 50,
      "deuce_place": 50,
      "ad_spin": 50,
      "ad_place": 50,
      "pressure_play_risk": 75,
      "return_position": 50,
      "movement_aggression": 80,
      "time_btwn_points": 50,
      "slice_usage": 60
    },
    "created_at": "2026-03-01T19:25:21.962644+00:00"
  },
  "preset-003": {
    "id": "preset-003",
    "title": "Rafael Nadal Custom",
    "description": "Rafael Nadal's custom loadout.",
    "is_default": false,
    "sliders": {
      "fh_power": 20,
      "fh_spin": 99,
      "bh_power": 20,
      "bh_spin": 85,
      "serve_power": 70,
      "serve_spin": 95,
      "shot_dir_risk": 35,
      "serve_variety": 30,
      "drop_frequency": 15,
      "deuce_spin": 85,
      "deuce_place": 25,
      "ad_spin": 85,
      "ad_place": 75,
      "pressure_play_risk": 20,
      "return_position": 10,
      "movement_aggression": 35,
      "time_btwn_points": 99,
      "slice_usage": 30
    },
    "created_at": "2026-03-01T19:29:59.017895+00:00"
  },
  "preset-004": {
    "id": "preset-004",
    "title": "Novak Djokovic Custom",
    "description": "Novak Djokovic's custom loadout.",
    "is_default": false,
    "sliders": {
      "fh_power": 90,
      "fh_spin": 20,
      "bh_power": 90,
      "bh_spin": 20,
      "serve_power": 85,
      "serve_spin": 30,
      "shot_dir_risk": 85,
      "serve_variety": 80,
      "drop_frequency": 10,
      "deuce_spin": 20,
      "deuce_place": 71,
      "ad_spin": 30,
      "ad_place": 45,
      "pressure_play_risk": 65,
      "return_position": 91,
      "movement_aggression": 70,
      "time_btwn_points": 96,
      "slice_usage": 35
    },
    "created_at": "2026-03-01T19:29:59.029091+00:00"
  },
  "preset-005": {
    "id": "preset-005",
    "title": "Roger Federer Custom",
    "description": "Roger Federer's custom loadout.",
    "is_default": false,
    "sliders": {
      "fh_power": 90,
      "fh_spin": 40,
      "bh_power": 70,
      "bh_spin": 30,
      "serve_power": 95,
      "serve_spin": 50,
      "shot_dir_risk": 95,
      "serve_variety": 95,
      "drop_frequency": 35,
      "deuce_spin": 20,
      "deuce_place": 71,
      "ad_spin": 30,
      "ad_place": 45,
      "pressure_play_risk": 85,
      "return_position": 85,
      "movement_aggression": 85,
      "time_btwn_points": 50,
      "slice_usage": 65
    },
    "created_at": "2026-03-01T19:29:59.029091+00:00"
  },
  "preset-006": {
    "id": "preset-006",
    "title": "Carlos Alcaraz Custom",
    "description": "",
    "is_default": false,
    "sliders": {
      "fh_power": 100,
      "fh_spin": 100,
      "bh_power": 80,
      "bh_spin": 75,
      "serve_power": 75,
      "serve_spin": 80,
      "shot_dir_risk": 90,
      "serve_variety": 85,
      "drop_frequency": 75,
      "deuce_spin": 50,
      "deuce_place": 50,
      "ad_spin": 50,
      "ad_place": 50,
      "pressure_play_risk": 90,
      "return_position": 80,
      "movement_aggression": 95,
      "time_btwn_points": 70,
      "slice_usage": 45
    },
    "created_at": "2026-03-04T00:09:42.353798+00:00"
  },
  "preset-007": {
    "id": "preset-007",
    "title": "Jannik Sinner Custom",
    "description": "",
    "is_default": false,
    "sliders": {
      "fh_power": 95,
      "fh_spin": 40,
      "bh_power": 95,
      "bh_spin": 75,
      "serve_power": 85,
      "serve_spin": 65,
      "shot_dir_risk": 60,
      "serve_variety": 70,
      "drop_frequency": 30,
      "deuce_spin": 50,
      "deuce_place": 50,
      "ad_spin": 50,
      "ad_place": 50,
      "pressure_play_risk": 35,
      "return_position": 60,
      "movement_aggression": 60,
      "time_btwn_points": 40,
      "slice_usage": 10
    },
    "created_at": "2026-03-04T00:14:40.325159+00:00"
  }
}